im_jenkins_server.py
im_jenkins_utils-1.3.0.dist-info/LICENSE.txt
im_jenkins_utils-1.3.0.dist-info/METADATA
im_jenkins_utils-1.3.0.dist-info/WHEEL
im_jenkins_utils-1.3.0.dist-info/top_level.txt
im_jenkins_utils-1.3.0.dist-info/RECORD
