Metadata-Version: 2.1
Name: im-jenkins-utils
Version: 1.3.0
Summary: Utilities for Informatics Matters CI/CD configuration
Home-page: https://github.com/InformaticsMatters/jenkins-utils
Author: Alan Christie
Author-email: achristie@informaticsmatters.com
License: Copyright (C) 2020 Informatics Matters Ltd. All rights reserved.
Keywords: jenkins
Platform: any
Classifier: Development Status :: 5 - Production/Stable
Classifier: Environment :: Console
Classifier: Intended Audience :: Developers
Classifier: License :: OSI Approved :: MIT License
Classifier: Programming Language :: Python :: 3.6
Classifier: Topic :: Software Development :: Build Tools
Requires-Python: >=3, <4
Requires-Dist: python-jenkins (==1.3.*)
